vidstab/VidStab.py
vidstab/__init__.py
vidstab/__main__.py
vidstab/auto_border_utils.py
vidstab/border_utils.py
vidstab/cv2_utils.py
vidstab/download_videos.py
vidstab/frame.py
vidstab/frame_queue.py
vidstab/general_utils.py
vidstab/layer_utils.py
vidstab/main_utils.py
vidstab/plot_utils.py
vidstab/pop_deque.py
vidstab/version.py
vidstab/vidstab_utils.py
vidstab-1.7.4.dist-info/LICENSE
vidstab-1.7.4.dist-info/METADATA
vidstab-1.7.4.dist-info/WHEEL
vidstab-1.7.4.dist-info/top_level.txt
vidstab-1.7.4.dist-info/RECORD
