Metadata-Version: 2.1
Name: vidstab
Version: 1.7.4
Summary: Video Stabilization using OpenCV
Home-page: https://github.com/AdamSpannbauer/python_video_stab
Author: Adam Spannbauer
Author-email: spannbaueradam@gmail.com
License: MIT
Keywords: video stabilization,computer vision,image processing,opencv
Platform: UNKNOWN
Classifier: Programming Language :: Python :: 3
Classifier: License :: OSI Approved :: MIT License
Classifier: Operating System :: OS Independent
Requires-Python: >=3.6
License-File: LICENSE
Requires-Dist: numpy
Requires-Dist: imutils (>=0.5.2)
Requires-Dist: progress
Requires-Dist: matplotlib
Provides-Extra: cv2
Requires-Dist: opencv-contrib-python (>=3.4.0) ; extra == 'cv2'
